statisticalagreement/__init__.py
statisticalagreement/__init__.pyi
statisticalagreement/core/__init__.py
statisticalagreement/core/_categorical_agreement.py
statisticalagreement/core/_continuous_agreement.py
statisticalagreement/core/_continuous_agreement.pyi
statisticalagreement/core/_methods.py
statisticalagreement/core/_types.py
statisticalagreement/core/agreement.py
statisticalagreement/core/classutils.py
statisticalagreement/core/mathutils.py
statisticalagreement/simulation/__init__.py
statisticalagreement/simulation/mc_simulation.py
statisticalagreement/simulation/monte_carlo.py
statisticalagreement-0.6.0.dist-info/METADATA
statisticalagreement-0.6.0.dist-info/WHEEL
statisticalagreement-0.6.0.dist-info/licenses/LICENSE
statisticalagreement-0.6.0.dist-info/RECORD
