Metadata-Version: 2.4
Name: statisticalagreement
Version: 0.6.0
Summary: Implementation of indexes used in statistical agreement
Project-URL: Homepage, https://github.com/remyCases/StatisticalAgreement
Project-URL: Bug Tracker, https://github.com/remyCases/StatisticalAgreement/issues
Author-email: Cases Rémy <remy.cases@gmail.com>
License-File: LICENSE
Classifier: License :: OSI Approved :: MIT License
Classifier: Operating System :: OS Independent
Classifier: Programming Language :: Python :: 3
Requires-Python: >=3.10
Requires-Dist: attrs>=24.1.0
Requires-Dist: numpy>=1.22.0
Requires-Dist: scipy>=1.10
